Metadata-Version: 1.0
Name: big-holes-in-big-data
Version: 0.2
Summary: find empty hyperrectangles in high-dimensional point clouds
Home-page: https://github.com/pavelkomarov/big-holes-in-big-data
Author: Pavel Komarov
Author-email: pvlkmrv@gmail.com
License: BSD
Platform: UNKNOWN
